LICENSE
MANIFEST.in
README.rst
setup.py
cerial/__init__.py
cerial/fields.py
cerial/serializers.py
cerial/tests/__init__.py
cerial/tests/manage.py
cerial/tests/settings.py
cerial/tests/urls.py
cerial/tests/testapp/__init__.py
cerial/tests/testapp/models.py
cerial/tests/testapp/tests.py
cerial/tests/testapp/views.py
django_cerial.egg-info/PKG-INFO
django_cerial.egg-info/SOURCES.txt
django_cerial.egg-info/dependency_links.txt
django_cerial.egg-info/not-zip-safe
django_cerial.egg-info/top_level.txt